openagua_client/__init__.py
openagua_client/client.py
openagua_client-0.2.3.dist-info/LICENSE
openagua_client-0.2.3.dist-info/METADATA
openagua_client-0.2.3.dist-info/WHEEL
openagua_client-0.2.3.dist-info/top_level.txt
openagua_client-0.2.3.dist-info/RECORD
