Metadata-Version: 2.1
Name: openagua-client
Version: 0.2.3
Summary: A very thin wrapper around the OpenAgua web API
Home-page: https://github.com/openagua/openagua-client
Author: David Rheinheimer
Author-email: david.rheinheimer@tec.mx
License: MIT
Classifier: Programming Language :: Python :: 3
Classifier: License :: OSI Approved :: MIT License
Classifier: Operating System :: OS Independent
Requires-Python: >=3.6
License-File: LICENSE
Requires-Dist: requests
